Workbook

Sheet Login
A1: Project Name | B1: UMPay Mobile
A2: Module/Feature Name | B2: Login | P2: HIGH | Q2: MEDIUM | R2: LOW
A3: Reference Document | B3: UMPayLogin.feature | N3: PASS | O3: =COUNTIF(K:K,"PASS") | P3: =COUNTIFS(K:K,"PASS",L:L,"HIGH") | Q3: =COUNTIFS(K:K,"PASS",L:L,"MEDIUM") | R3: =COUNTIFS(K:K,"PASS",L:L,"LOW")
A4: Created By | B4: KIMA | N4: FAIL | O4: =COUNTIF(K:K,"FAIL") | P4: =COUNTIFS(K:K,"FAIL",L:L,"HIGH") | Q4: =COUNTIFS(K:K,"FAIL",L:L,"MEDIUM") | R4: =COUNTIFS(K:K,"FAIL",L:L,"LOW")
A5: Date of Creation | B5: 46274 | N5: PENDING | O5: =COUNTIF(K:K,"PENDING") | P5: =COUNTIFS(K:K,"PENDING",L:L,"HIGH") | Q5: =COUNTIFS(K:K,"PENDING",L:L,"MEDIUM") | R5: =COUNTIFS(K:K,"PENDING",L:L,"LOW")
A6: Date of Review | B6: 46274
A8: TEST CASE ID | B8: TEST SCENARIO | C8: TEST CASE | D8: TEST CATEGORY | E8: PRE-CONDITION | F8: TEST STEPS | G8: TEST DATA | H8: EXPECTED RESULTS | I8: POST CONDITION | J8: ACTUAL RESULT | K8: STATUS | L8: PRIORITY | M8: TESTER | N8: TEST DATE | O8: DEVICE | P8: PLATFORM | Q8: ISSUE LINK | R8: COMMENT | S8: Run
A9: TC_001 | B9: Login | C9: The app opens on a login screen offering both sign in methods | D9: Positive | E9: The UMPay app is open on the login screen | F9: -Given the UMPay app is open on the login screen -Then the login screen should offer both sign in methods | G9: Valid UMPay account | H9: The login screen should offer both sign in methods | I9: The app is left on the screen the scenario reached | J9: Ran on Redmi 13C (Android) and behaved as the scenario expects | K9: PASS | L9: HIGH | M9: KIMA | N9: 46274 | O9: Redmi 13C (Android) | P9: UMPay Android app | S9: Run
A10: TC_002 | B10: Login | C10: A valid account signs in and reaches the dashboard | D10: Positive | E10: The UMPay app is open on the login screen | F10: -Given the UMPay app is open on the login screen -When I sign in with the credentials in "<row>" of "<excelSheetName>" of "<excelFileName>" -Then I should reach the dashboard -And the dashboard should offer the money actions | G10: Login_TestData.xlsx | H10: I should reach the dashboard; the dashboard should offer the money actions | I10: The app is left on the screen the scenario reached | J10: Ran on Redmi 13C (Android) and behaved as the scenario expects | K10: PASS | L10: HIGH | M10: KIMA | N10: 46274 | O10: Redmi 13C (Android) | P10: UMPay Android app | S10: Run
A11: TC_003 | B11: Login | C11: A signed in user can sign out again | D11: Positive | E11: I log into the UMPay application with valid credentials | F11: -Given I log into the UMPay application with valid credentials using "<row>" of "<excelSheetName>" of "<excelFileName>" -When I sign out -Then I should be back on the login screen | G11: Login_TestData.xlsx | H11: I should be back on the login screen | I11: The app is left on the screen the scenario reached | J11: Ran on Redmi 13C (Android) and behaved as the scenario expects | K11: PASS | L11: HIGH | M11: KIMA | N11: 46274 | O11: Redmi 13C (Android) | P11: UMPay Android app | S11: Run

Sheet Register
A1: Project Name | B1: UMPay Mobile
A2: Module/Feature Name | B2: Register | P2: HIGH | Q2: MEDIUM | R2: LOW
A3: Reference Document | B3: Register.feature | N3: PASS | O3: =COUNTIF(K:K,"PASS") | P3: =COUNTIFS(K:K,"PASS",L:L,"HIGH") | Q3: =COUNTIFS(K:K,"PASS",L:L,"MEDIUM") | R3: =COUNTIFS(K:K,"PASS",L:L,"LOW")
A4: Created By | B4: KIMA | N4: FAIL | O4: =COUNTIF(K:K,"FAIL") | P4: =COUNTIFS(K:K,"FAIL",L:L,"HIGH") | Q4: =COUNTIFS(K:K,"FAIL",L:L,"MEDIUM") | R4: =COUNTIFS(K:K,"FAIL",L:L,"LOW")
A5: Date of Creation | B5: 46274 | N5: PENDING | O5: =COUNTIF(K:K,"PENDING") | P5: =COUNTIFS(K:K,"PENDING",L:L,"HIGH") | Q5: =COUNTIFS(K:K,"PENDING",L:L,"MEDIUM") | R5: =COUNTIFS(K:K,"PENDING",L:L,"LOW")
A6: Date of Review | B6: 46274
A8: TEST CASE ID | B8: TEST SCENARIO | C8: TEST CASE | D8: TEST CATEGORY | E8: PRE-CONDITION | F8: TEST STEPS | G8: TEST DATA | H8: EXPECTED RESULTS | I8: POST CONDITION | J8: ACTUAL RESULT | K8: STATUS | L8: PRIORITY | M8: TESTER | N8: TEST DATE | O8: DEVICE | P8: PLATFORM | Q8: ISSUE LINK | R8: COMMENT | S8: Run
A9: TC_001 | B9: Register | C9: A new account is registered and the app asks to verify the email address | D9: Positive | E9: The UMPay app is open on the login screen | F9: -Given the UMPay app is open on the login screen -When I open the registration form -And I fill in the registration form using "<row>" of "<excelSheetName>" of "<excelFileName>" -And I solve the captcha and submit the form -Then the app should ask for the emailed verification code -And the app is closed | G9: Register_TestData.xlsx | H9: The app should ask for the emailed verification code; the app is closed | I9: The app is left on the screen the scenario reached | J9: Not run in this pass. The runner holds @register and @e2e back from an unattended run - a registration makes a real account, solves a captcha and reads a code out of a mailbox, and the journey drives every form a second time on the one device this suite has. Launch it on its own with the Run link beside this row | K9: PENDING | L9: MEDIUM | M9: KIMA | N9: 46274 | O9: Redmi 13C (Android) | P9: UMPay Android app | S9: Run

Sheet Deposit
A1: Project Name | B1: UMPay Mobile
A2: Module/Feature Name | B2: Deposit | P2: HIGH | Q2: MEDIUM | R2: LOW
A3: Reference Document | B3: Deposit.feature | N3: PASS | O3: =COUNTIF(K:K,"PASS") | P3: =COUNTIFS(K:K,"PASS",L:L,"HIGH") | Q3: =COUNTIFS(K:K,"PASS",L:L,"MEDIUM") | R3: =COUNTIFS(K:K,"PASS",L:L,"LOW")
A4: Created By | B4: KIMA | N4: FAIL | O4: =COUNTIF(K:K,"FAIL") | P4: =COUNTIFS(K:K,"FAIL",L:L,"HIGH") | Q4: =COUNTIFS(K:K,"FAIL",L:L,"MEDIUM") | R4: =COUNTIFS(K:K,"FAIL",L:L,"LOW")
A5: Date of Creation | B5: 46274 | N5: PENDING | O5: =COUNTIF(K:K,"PENDING") | P5: =COUNTIFS(K:K,"PENDING",L:L,"HIGH") | Q5: =COUNTIFS(K:K,"PENDING",L:L,"MEDIUM") | R5: =COUNTIFS(K:K,"PENDING",L:L,"LOW")
A6: Date of Review | B6: 46274
A8: TEST CASE ID | B8: TEST SCENARIO | C8: TEST CASE | D8: TEST CATEGORY | E8: PRE-CONDITION | F8: TEST STEPS | G8: TEST DATA | H8: EXPECTED RESULTS | I8: POST CONDITION | J8: ACTUAL RESULT | K8: STATUS | L8: PRIORITY | M8: TESTER | N8: TEST DATE | O8: DEVICE | P8: PLATFORM | Q8: ISSUE LINK | R8: COMMENT | S8: Run
A9: TC_001 | B9: Deposit | C9: A deposit asks for payment details before it can be confirmed | D9: Positive | E9: I log into the UMPay application with valid credentials | F9: -Given I log into the UMPay application with valid credentials using "<row>" of "<excelSheetName>" of "<excelFileName>" -When I open the "Deposit" form from the dashboard -Then the "Deposit" form should be shown -And the "Confirm" action should be disabled -When I enter the deposit amount in "<row>" of "<excelSheetName>" of "<excelFileName>" -Then the amount should be accepted -And the form should ask for "Payment information" -And the "Confirm" action should be disabled -And the transaction is deliberately not submitted | G9: Deposit_TestData.xlsx | H9: The "Deposit" form should be shown; the "Confirm" action should be disabled; the amount should be accepted; the form should ask for "Payment information"; the transaction is deliberately not submitted | I9: The app is left on the screen the scenario reached | J9: Ran on Redmi 13C (Android) and behaved as the scenario expects | K9: PASS | L9: MEDIUM | M9: KIMA | N9: 46274 | O9: Redmi 13C (Android) | P9: UMPay Android app | S9: Run

Sheet Withdraw
A1: Project Name | B1: UMPay Mobile
A2: Module/Feature Name | B2: Withdraw | P2: HIGH | Q2: MEDIUM | R2: LOW
A3: Reference Document | B3: Withdraw.feature | N3: PASS | O3: =COUNTIF(K:K,"PASS") | P3: =COUNTIFS(K:K,"PASS",L:L,"HIGH") | Q3: =COUNTIFS(K:K,"PASS",L:L,"MEDIUM") | R3: =COUNTIFS(K:K,"PASS",L:L,"LOW")
A4: Created By | B4: KIMA | N4: FAIL | O4: =COUNTIF(K:K,"FAIL") | P4: =COUNTIFS(K:K,"FAIL",L:L,"HIGH") | Q4: =COUNTIFS(K:K,"FAIL",L:L,"MEDIUM") | R4: =COUNTIFS(K:K,"FAIL",L:L,"LOW")
A5: Date of Creation | B5: 46274 | N5: PENDING | O5: =COUNTIF(K:K,"PENDING") | P5: =COUNTIFS(K:K,"PENDING",L:L,"HIGH") | Q5: =COUNTIFS(K:K,"PENDING",L:L,"MEDIUM") | R5: =COUNTIFS(K:K,"PENDING",L:L,"LOW")
A6: Date of Review | B6: 46274
A8: TEST CASE ID | B8: TEST SCENARIO | C8: TEST CASE | D8: TEST CATEGORY | E8: PRE-CONDITION | F8: TEST STEPS | G8: TEST DATA | H8: EXPECTED RESULTS | I8: POST CONDITION | J8: ACTUAL RESULT | K8: STATUS | L8: PRIORITY | M8: TESTER | N8: TEST DATE | O8: DEVICE | P8: PLATFORM | Q8: ISSUE LINK | R8: COMMENT | S8: Run
A9: TC_001 | B9: Withdraw | C9: A withdrawal is validated before it can be confirmed | D9: Positive | E9: I log into the UMPay application with valid credentials | F9: -Given I log into the UMPay application with valid credentials using "<row>" of "<excelSheetName>" of "<excelFileName>" -When I open the "Withdrawal" form from the dashboard -Then the "Withdrawal" form should be shown -When I enter the withdrawal amount in "<row>" of "<excelSheetName>" of "<excelFileName>" -Then the amount should be accepted -And the transaction is deliberately not submitted | G9: Withdraw_TestData.xlsx | H9: The "Withdrawal" form should be shown; the amount should be accepted; the transaction is deliberately not submitted | I9: The app is left on the screen the scenario reached | J9: BLOCKED, not failed - the device lost its network mid-run and the app answered "Network Error - Please check your internet connection", so signing in never completed and the scenario could not begin. Nothing here is a verdict on the application | K9: PENDING | L9: MEDIUM | M9: KIMA | N9: 46274 | O9: Redmi 13C (Android) | P9: UMPay Android app | S9: Run

Sheet Transfer
A1: Project Name | B1: UMPay Mobile
A2: Module/Feature Name | B2: Transfer | P2: HIGH | Q2: MEDIUM | R2: LOW
A3: Reference Document | B3: Transfer.feature | N3: PASS | O3: =COUNTIF(K:K,"PASS") | P3: =COUNTIFS(K:K,"PASS",L:L,"HIGH") | Q3: =COUNTIFS(K:K,"PASS",L:L,"MEDIUM") | R3: =COUNTIFS(K:K,"PASS",L:L,"LOW")
A4: Created By | B4: KIMA | N4: FAIL | O4: =COUNTIF(K:K,"FAIL") | P4: =COUNTIFS(K:K,"FAIL",L:L,"HIGH") | Q4: =COUNTIFS(K:K,"FAIL",L:L,"MEDIUM") | R4: =COUNTIFS(K:K,"FAIL",L:L,"LOW")
A5: Date of Creation | B5: 46274 | N5: PENDING | O5: =COUNTIF(K:K,"PENDING") | P5: =COUNTIFS(K:K,"PENDING",L:L,"HIGH") | Q5: =COUNTIFS(K:K,"PENDING",L:L,"MEDIUM") | R5: =COUNTIFS(K:K,"PENDING",L:L,"LOW")
A6: Date of Review | B6: 46274
A8: TEST CASE ID | B8: TEST SCENARIO | C8: TEST CASE | D8: TEST CATEGORY | E8: PRE-CONDITION | F8: TEST STEPS | G8: TEST DATA | H8: EXPECTED RESULTS | I8: POST CONDITION | J8: ACTUAL RESULT | K8: STATUS | L8: PRIORITY | M8: TESTER | N8: TEST DATE | O8: DEVICE | P8: PLATFORM | Q8: ISSUE LINK | R8: COMMENT | S8: Run
A9: TC_001 | B9: Transfer | C9: The transfer hub offers every destination | D9: Positive | E9: I log into the UMPay application with valid credentials | F9: -Given I log into the UMPay application with valid credentials using "1" of "Sheet1" of "Login_TestData.xlsx" -When I open the transfer hub -Then the transfer hub should offer the route "UMPay to Existing template" -And the transfer hub should offer the route "UMPay to UMPay Wallet" -And the transfer hub should offer the route "UnionPay China" -And the transfer hub should offer the route "UnionPay Global" -And the transfer hub should offer the route "Transfer to AliPay" -And the transfer hub should offer the route "Transfer to WeChat" | G9: Login_TestData.xlsx | H9: The transfer hub should offer the route "UMPay to Existing template"; the transfer hub should offer the route "UMPay to UMPay Wallet"; the transfer hub should offer the route "UnionPay China"; the transfer hub should offer the route "UnionPay Global"; the transfer hub should offer the route "Transfer to AliPay"; the transfer hub should offer the route "Transfer to WeChat" | I9: The app is left on the screen the scenario reached | J9: Ran on Redmi 13C (Android) and behaved as the scenario expects | K9: PASS | L9: MEDIUM | M9: KIMA | N9: 46274 | O9: Redmi 13C (Android) | P9: UMPay Android app | S9: Run
A10: TC_002 | B10: Transfer | C10: A payment app route under maintenance refuses to open | D10: Negative | E10: I log into the UMPay application with valid credentials | F10: -Given I log into the UMPay application with valid credentials using "1" of "Sheet1" of "Login_TestData.xlsx" -When I open the transfer hub -When I take the "<route>" route -Then the app should say the service is unavailable | G10: Login_TestData.xlsx | H10: The app should say the service is unavailable | I10: The app is left on the screen the scenario reached | J10: Ran on Redmi 13C (Android) and behaved as the scenario expects | K10: PASS | L10: HIGH | M10: KIMA | N10: 46274 | O10: Redmi 13C (Android) | P10: UMPay Android app | S10: Run
A11: TC_003 | B11: Transfer | C11: The saved template route opens the list of payees | D11: Positive | E11: I log into the UMPay application with valid credentials | F11: -Given I log into the UMPay application with valid credentials using "1" of "Sheet1" of "Login_TestData.xlsx" -When I open the transfer hub -When I take the "UMPay to Existing template" route -Then the saved template list should be shown -And the template list should hold at least one saved payee | G11: Login_TestData.xlsx | H11: The saved template list should be shown; the template list should hold at least one saved payee | I11: The app is left on the screen the scenario reached | J11: Ran on Redmi 13C (Android) and behaved as the scenario expects | K11: PASS | L11: MEDIUM | M11: KIMA | N11: 46274 | O11: Redmi 13C (Android) | P11: UMPay Android app | S11: Run
A12: TC_004 | B12: Transfer | C12: The wallet transfer form asks for everything a wallet transfer needs | D12: Positive | E12: I log into the UMPay application with valid credentials | F12: -Given I log into the UMPay application with valid credentials using "1" of "Sheet1" of "Login_TestData.xlsx" -When I open the transfer hub -When I take the "UMPay to UMPay Wallet" route -Then the wallet transfer form should be shown -And the wallet form should show the sending wallet and its balance -And the wallet form should offer a destination wallet field -And the wallet form should ask for "Transfer Amount" -And the wallet form should ask for "Minimum: 100.0" -And the wallet form should ask for "Select who will pay the fee" -And the wallet form should ask for "Create template" -And the wallet form should ask for "Remark" | G12: Login_TestData.xlsx | H12: The wallet transfer form should be shown; the wallet form should show the sending wallet and its balance; the wallet form should offer a destination wallet field; the wallet form should ask for "Transfer Amount"; the wallet form should ask for "Minimum: 100.0"; the wallet form should ask for "Select who will pay the fee"; the wallet form should ask for "Create template"; the wallet form should ask for "Remark" | I12: The app is left on the screen the scenario reached | J12: Ran on Redmi 13C (Android) and behaved as the scenario expects | K12: PASS | L12: MEDIUM | M12: KIMA | N12: 46274 | O12: Redmi 13C (Android) | P12: UMPay Android app | S12: Run
A13: TC_005 | B13: Transfer | C13: A wallet transfer cannot be sent from an empty form | D13: Negative | E13: I log into the UMPay application with valid credentials | F13: -Given I log into the UMPay application with valid credentials using "1" of "Sheet1" of "Login_TestData.xlsx" -When I open the transfer hub -When I take the "UMPay to UMPay Wallet" route -Then the wallet transfer form should be shown -And the wallet transfer should not be sendable yet -And the transfer is deliberately not sent | G13: Login_TestData.xlsx | H13: The wallet transfer form should be shown; the wallet transfer should not be sendable yet; the transfer is deliberately not sent | I13: The app is left on the screen the scenario reached | J13: Ran on Redmi 13C (Android) and behaved as the scenario expects | K13: PASS | L13: HIGH | M13: KIMA | N13: 46274 | O13: Redmi 13C (Android) | P13: UMPay Android app | S13: Run
A14: TC_006 | B14: Transfer | C14: Either party can be chosen to pay the wallet transfer fee | D14: Positive | E14: I log into the UMPay application with valid credentials | F14: -Given I log into the UMPay application with valid credentials using "1" of "Sheet1" of "Login_TestData.xlsx" -When I open the transfer hub -When I take the "UMPay to UMPay Wallet" route -Then the wallet transfer form should be shown -And the wallet form should offer both parties as the fee payer -When I choose "Fee will be paid by me" to pay the fee -Then the fee payer choice "Fee will be paid by other party" should still be offered -When I choose "Fee will be paid by other party" to pay the fee -Then the fee payer choice "Fee will be paid by me" should still be offered | G14: Login_TestData.xlsx | H14: The wallet transfer form should be shown; the wallet form should offer both parties as the fee payer; the fee payer choice "Fee will be paid by other party" should still be offered; the fee payer choice "Fee will be paid by me" should still be offered | I14: The app is left on the screen the scenario reached | J14: Ran on Redmi 13C (Android) and behaved as the scenario expects | K14: PASS | L14: MEDIUM | M14: KIMA | N14: 46274 | O14: Redmi 13C (Android) | P14: UMPay Android app | S14: Run
A15: TC_007 | B15: Transfer | C15: The wallet remark box counts the characters left | D15: Positive | E15: I log into the UMPay application with valid credentials | F15: -Given I log into the UMPay application with valid credentials using "1" of "Sheet1" of "Login_TestData.xlsx" -When I open the transfer hub -When I take the "UMPay to UMPay Wallet" route -Then the wallet transfer form should be shown -And the remark box should report "150 characters remaining" -When I write "Rent" in the wallet remark box -Then the remark box should report "146 characters remaining" | G15: Login_TestData.xlsx | H15: The wallet transfer form should be shown; the remark box should report "150 characters remaining"; the remark box should report "146 characters remaining" | I15: The app is left on the screen the scenario reached | J15: Ran on Redmi 13C (Android) and behaved as the scenario expects | K15: PASS | L15: MEDIUM | M15: KIMA | N15: 46274 | O15: Redmi 13C (Android) | P15: UMPay Android app | S15: Run

Sheet Convert
A1: Project Name | B1: UMPay Mobile
A2: Module/Feature Name | B2: Convert | P2: HIGH | Q2: MEDIUM | R2: LOW
A3: Reference Document | B3: Convert.feature | N3: PASS | O3: =COUNTIF(K:K,"PASS") | P3: =COUNTIFS(K:K,"PASS",L:L,"HIGH") | Q3: =COUNTIFS(K:K,"PASS",L:L,"MEDIUM") | R3: =COUNTIFS(K:K,"PASS",L:L,"LOW")
A4: Created By | B4: KIMA | N4: FAIL | O4: =COUNTIF(K:K,"FAIL") | P4: =COUNTIFS(K:K,"FAIL",L:L,"HIGH") | Q4: =COUNTIFS(K:K,"FAIL",L:L,"MEDIUM") | R4: =COUNTIFS(K:K,"FAIL",L:L,"LOW")
A5: Date of Creation | B5: 46274 | N5: PENDING | O5: =COUNTIF(K:K,"PENDING") | P5: =COUNTIFS(K:K,"PENDING",L:L,"HIGH") | Q5: =COUNTIFS(K:K,"PENDING",L:L,"MEDIUM") | R5: =COUNTIFS(K:K,"PENDING",L:L,"LOW")
A6: Date of Review | B6: 46274
A8: TEST CASE ID | B8: TEST SCENARIO | C8: TEST CASE | D8: TEST CATEGORY | E8: PRE-CONDITION | F8: TEST STEPS | G8: TEST DATA | H8: EXPECTED RESULTS | I8: POST CONDITION | J8: ACTUAL RESULT | K8: STATUS | L8: PRIORITY | M8: TESTER | N8: TEST DATE | O8: DEVICE | P8: PLATFORM | Q8: ISSUE LINK | R8: COMMENT | S8: Run
A9: TC_001 | B9: Convert | C9: A conversion prices the amount and offers to convert | D9: Positive | E9: I log into the UMPay application with valid credentials | F9: -Given I log into the UMPay application with valid credentials using "<row>" of "<excelSheetName>" of "<excelFileName>" -When I open the "Convert" form from the dashboard -Then the "Convert" form should be shown -When I enter the conversion amount in "<row>" of "<excelSheetName>" of "<excelFileName>" -Then the amount should be accepted -And the transaction is deliberately not submitted | G9: Convert_TestData.xlsx | H9: The "Convert" form should be shown; the amount should be accepted; the transaction is deliberately not submitted | I9: The app is left on the screen the scenario reached | J9: BLOCKED, not failed - the device lost its network mid-run and the app answered "Network Error - Please check your internet connection", so signing in never completed and the scenario could not begin. Nothing here is a verdict on the application | K9: PENDING | L9: MEDIUM | M9: KIMA | N9: 46274 | O9: Redmi 13C (Android) | P9: UMPay Android app | S9: Run

Sheet Global_Transfer
A1: Project Name | B1: UMPay Mobile
A2: Module/Feature Name | B2: Global Transfer | P2: HIGH | Q2: MEDIUM | R2: LOW
A3: Reference Document | B3: GlobalTransfer.feature | N3: PASS | O3: =COUNTIF(K:K,"PASS") | P3: =COUNTIFS(K:K,"PASS",L:L,"HIGH") | Q3: =COUNTIFS(K:K,"PASS",L:L,"MEDIUM") | R3: =COUNTIFS(K:K,"PASS",L:L,"LOW")
A4: Created By | B4: KIMA | N4: FAIL | O4: =COUNTIF(K:K,"FAIL") | P4: =COUNTIFS(K:K,"FAIL",L:L,"HIGH") | Q4: =COUNTIFS(K:K,"FAIL",L:L,"MEDIUM") | R4: =COUNTIFS(K:K,"FAIL",L:L,"LOW")
A5: Date of Creation | B5: 46274 | N5: PENDING | O5: =COUNTIF(K:K,"PENDING") | P5: =COUNTIFS(K:K,"PENDING",L:L,"HIGH") | Q5: =COUNTIFS(K:K,"PENDING",L:L,"MEDIUM") | R5: =COUNTIFS(K:K,"PENDING",L:L,"LOW")
A6: Date of Review | B6: 46274
A8: TEST CASE ID | B8: TEST SCENARIO | C8: TEST CASE | D8: TEST CATEGORY | E8: PRE-CONDITION | F8: TEST STEPS | G8: TEST DATA | H8: EXPECTED RESULTS | I8: POST CONDITION | J8: ACTUAL RESULT | K8: STATUS | L8: PRIORITY | M8: TESTER | N8: TEST DATE | O8: DEVICE | P8: PLATFORM | Q8: ISSUE LINK | R8: COMMENT | S8: Run
A9: TC_001 | B9: Global Transfer | C9: UnionPay China states its limits before anything is entered | D9: Positive | E9: I log into the UMPay application with valid credentials | F9: -Given I log into the UMPay application with valid credentials using "1" of "Sheet1" of "Login_TestData.xlsx" -When I open the transfer hub -And I take the "UnionPay China" route -Then the UnionPay transfer form should be shown -And the UnionPay form should state "Pay Currency" -And the UnionPay form should state "Receive Currency" -And the UnionPay form should state "Card Available Balance" -And the UnionPay form should state "Limit Min 10.00 USD" -And the UnionPay form should state "Limit Max 10,000.00 USD" -And the UnionPay transfer should not be sendable yet -And the transfer should not be priced | G9: Login_TestData.xlsx | H9: The UnionPay transfer form should be shown; the UnionPay form should state "Pay Currency"; the UnionPay form should state "Receive Currency"; the UnionPay form should state "Card Available Balance"; the UnionPay form should state "Limit Min 10.00 USD"; the UnionPay form should state "Limit Max 10,000.00 USD"; the UnionPay transfer should not be sendable yet; the transfer should not be priced | I9: The app is left on the screen the scenario reached | J9: BLOCKED, not failed - the driver answered with an unknown server-side error, so the scenario never reached the point of asking the application anything: org.openqa.selenium.WebDriverException: An unknown server-side error occurred while processing the command. Original error: Could not proxy command to | K9: PENDING | L9: MEDIUM | M9: KIMA | N9: 46274 | O9: Redmi 13C (Android) | P9: UMPay Android app | S9: Run
A10: TC_002 | B10: Global Transfer | C10: UnionPay China prices the transfer once a valid amount is entered | D10: Positive | E10: I log into the UMPay application with valid credentials | F10: -Given I log into the UMPay application with valid credentials using "<row>" of "<excelSheetName>" of "<excelFileName>" -When I open the transfer hub -And I take the "UnionPay China" route -Then the UnionPay transfer form should be shown -When I enter the UnionPay amount in "<row>" of "<excelSheetName>" of "<excelFileName>" -Then the transfer should be priced -And the priced transfer should show "Original Amount" -And the priced transfer should show "Estimate Rate" -And the priced transfer should show "Fee" -And the priced transfer should show "Total Amount" -And the priced transfer should show "Approximate Received" -And the UnionPay transfer should become sendable -And the transfer is deliberately not sent | G10: GlobalTransfer_TestData.xlsx | H10: The UnionPay transfer form should be shown; the transfer should be priced; the priced transfer should show "Original Amount"; the priced transfer should show "Estimate Rate"; the priced transfer should show "Fee"; the priced transfer should show "Total Amount"; the priced transfer should show "Approximate Received"; the UnionPay transfer should become sendable | I10: The app is left on the screen the scenario reached | J10: java.lang.AssertionError: The Transfer action never became enabled on a priced form expected [true] but found [false] | K10: FAIL | L10: MEDIUM | M10: KIMA | N10: 46274 | O10: Redmi 13C (Android) | P10: UMPay Android app | S10: Run
A11: TC_003 | B11: Global Transfer | C11: UnionPay China refuses an amount below its minimum | D11: Negative | E11: I log into the UMPay application with valid credentials | F11: -Given I log into the UMPay application with valid credentials using "<row>" of "<excelSheetName>" of "<excelFileName>" -When I open the transfer hub -And I take the "UnionPay China" route -Then the UnionPay transfer form should be shown -When I enter the UnionPay amount in "<row>" of "<excelSheetName>" of "<excelFileName>" -Then the transfer should not be priced -And the UnionPay transfer should not be sendable yet | G11: GlobalTransfer_TestData.xlsx | H11: The UnionPay transfer form should be shown; the transfer should not be priced; the UnionPay transfer should not be sendable yet | I11: The app is left on the screen the scenario reached | J11: Ran on Redmi 13C (Android) and behaved as the scenario expects | K11: PASS | L11: HIGH | M11: KIMA | N11: 46274 | O11: Redmi 13C (Android) | P11: UMPay Android app | S11: Run
A12: TC_004 | B12: Global Transfer | C12: UnionPay Global offers the same form without a receive currency | D12: Negative | E12: I log into the UMPay application with valid credentials | F12: -Given I log into the UMPay application with valid credentials using "1" of "Sheet1" of "Login_TestData.xlsx" -When I open the transfer hub -And I take the "UnionPay Global" route -Then the UnionPay transfer form should be shown -And the UnionPay form should state "Pay Currency" -And the UnionPay form should state "Limit Min 10.00 USD" -And the UnionPay form should state "Limit Max 10,000.00 USD" -And the UnionPay form should state "Remark" -And the UnionPay form should not offer "Receive Currency" -And the UnionPay transfer should not be sendable yet | G12: Login_TestData.xlsx | H12: The UnionPay transfer form should be shown; the UnionPay form should state "Pay Currency"; the UnionPay form should state "Limit Min 10.00 USD"; the UnionPay form should state "Limit Max 10,000.00 USD"; the UnionPay form should state "Remark"; the UnionPay form should not offer "Receive Currency"; the UnionPay transfer should not be sendable yet | I12: The app is left on the screen the scenario reached | J12: Ran on Redmi 13C (Android) and behaved as the scenario expects | K12: PASS | L12: HIGH | M12: KIMA | N12: 46274 | O12: Redmi 13C (Android) | P12: UMPay Android app | S12: Run

Sheet Profile
A1: Project Name | B1: UMPay Mobile
A2: Module/Feature Name | B2: Profile | P2: HIGH | Q2: MEDIUM | R2: LOW
A3: Reference Document | B3: Profile.feature | N3: PASS | O3: =COUNTIF(K:K,"PASS") | P3: =COUNTIFS(K:K,"PASS",L:L,"HIGH") | Q3: =COUNTIFS(K:K,"PASS",L:L,"MEDIUM") | R3: =COUNTIFS(K:K,"PASS",L:L,"LOW")
A4: Created By | B4: KIMA | N4: FAIL | O4: =COUNTIF(K:K,"FAIL") | P4: =COUNTIFS(K:K,"FAIL",L:L,"HIGH") | Q4: =COUNTIFS(K:K,"FAIL",L:L,"MEDIUM") | R4: =COUNTIFS(K:K,"FAIL",L:L,"LOW")
A5: Date of Creation | B5: 46274 | N5: PENDING | O5: =COUNTIF(K:K,"PENDING") | P5: =COUNTIFS(K:K,"PENDING",L:L,"HIGH") | Q5: =COUNTIFS(K:K,"PENDING",L:L,"MEDIUM") | R5: =COUNTIFS(K:K,"PENDING",L:L,"LOW")
A6: Date of Review | B6: 46274
A8: TEST CASE ID | B8: TEST SCENARIO | C8: TEST CASE | D8: TEST CATEGORY | E8: PRE-CONDITION | F8: TEST STEPS | G8: TEST DATA | H8: EXPECTED RESULTS | I8: POST CONDITION | J8: ACTUAL RESULT | K8: STATUS | L8: PRIORITY | M8: TESTER | N8: TEST DATE | O8: DEVICE | P8: PLATFORM | Q8: ISSUE LINK | R8: COMMENT | S8: Run
A9: TC_001 | B9: Profile | C9: The profile panel offers everything the account holder can reach | D9: Positive | E9: I log into the UMPay application with valid credentials | F9: -Given I log into the UMPay application with valid credentials using "1" of "Sheet1" of "Login_TestData.xlsx" -When I open the profile panel -Then the profile panel should offer "Trade Record, User List, Commission Listing, Fee Listing, Wallets, Payment, Templates, Transfer Fee Setting, Security, Document verification, Language" | G9: Login_TestData.xlsx | H9: The profile panel should offer "Trade Record, User List, Commission Listing, Fee Listing, Wallets, Payment, Templates, Transfer Fee Setting, Security, Document verification, Language" | I9: The app is left on the screen the scenario reached | J9: Ran on Redmi 13C (Android) and behaved as the scenario expects | K9: PASS | L9: MEDIUM | M9: KIMA | N9: 46274 | O9: Redmi 13C (Android) | P9: UMPay Android app | S9: Run
A10: TC_002 | B10: Profile | C10: The profile panel shows the account's referral code | D10: Positive | E10: I log into the UMPay application with valid credentials | F10: -Given I log into the UMPay application with valid credentials using "1" of "Sheet1" of "Login_TestData.xlsx" -When I open the profile panel -Then the profile panel should show a referral code | G10: Login_TestData.xlsx | H10: The profile panel should show a referral code | I10: The app is left on the screen the scenario reached | J10: Ran on Redmi 13C (Android) and behaved as the scenario expects | K10: PASS | L10: MEDIUM | M10: KIMA | N10: 46274 | O10: Redmi 13C (Android) | P10: UMPay Android app | S10: Run
A11: TC_003 | B11: Profile | C11: Each destination in the profile panel opens its own screen | D11: Positive | E11: I log into the UMPay application with valid credentials | F11: -Given I log into the UMPay application with valid credentials using "1" of "Sheet1" of "Login_TestData.xlsx" -When I open the profile panel -And I open "<destination>" from the profile panel -Then the "<destination>" screen should open -When I go back from the destination -Then the profile panel should offer "<destination>" | G11: Login_TestData.xlsx | H11: The "<destination>" screen should open; the profile panel should offer "<destination>" | I11: The app is left on the screen the scenario reached | J11: Ran on Redmi 13C (Android) and behaved as the scenario expects | K11: PASS | L11: MEDIUM | M11: KIMA | N11: 46274 | O11: Redmi 13C (Android) | P11: UMPay Android app | S11: Run

Sheet End_To_End
A1: Project Name | B1: UMPay Mobile
A2: Module/Feature Name | B2: End To End | P2: HIGH | Q2: MEDIUM | R2: LOW
A3: Reference Document | B3: EndToEndTest.feature | N3: PASS | O3: =COUNTIF(K:K,"PASS") | P3: =COUNTIFS(K:K,"PASS",L:L,"HIGH") | Q3: =COUNTIFS(K:K,"PASS",L:L,"MEDIUM") | R3: =COUNTIFS(K:K,"PASS",L:L,"LOW")
A4: Created By | B4: KIMA | N4: FAIL | O4: =COUNTIF(K:K,"FAIL") | P4: =COUNTIFS(K:K,"FAIL",L:L,"HIGH") | Q4: =COUNTIFS(K:K,"FAIL",L:L,"MEDIUM") | R4: =COUNTIFS(K:K,"FAIL",L:L,"LOW")
A5: Date of Creation | B5: 46274 | N5: PENDING | O5: =COUNTIF(K:K,"PENDING") | P5: =COUNTIFS(K:K,"PENDING",L:L,"HIGH") | Q5: =COUNTIFS(K:K,"PENDING",L:L,"MEDIUM") | R5: =COUNTIFS(K:K,"PENDING",L:L,"LOW")
A6: Date of Review | B6: 46274
A8: TEST CASE ID | B8: TEST SCENARIO | C8: TEST CASE | D8: TEST CATEGORY | E8: PRE-CONDITION | F8: TEST STEPS | G8: TEST DATA | H8: EXPECTED RESULTS | I8: POST CONDITION | J8: ACTUAL RESULT | K8: STATUS | L8: PRIORITY | M8: TESTER | N8: TEST DATE | O8: DEVICE | P8: PLATFORM | Q8: ISSUE LINK | R8: COMMENT | S8: Run
A9: TC_001 | B9: End To End | C9: A user signs in, fills every money form, prices a transfer and signs out | D9: Positive | E9: The UMPay app is open on the login screen | F9: -Given the UMPay app is open on the login screen -When I sign in with the credentials in "1" of "Sheet1" of "Login_TestData.xlsx" -Then I should reach the dashboard -And the dashboard should offer the money actions -When I open the "Deposit" form from the dashboard -Then the "Deposit" form should be shown -And the "Confirm" action should be disabled -When I enter the deposit amount in "1" of "Sheet1" of "Deposit_TestData.xlsx" -Then the amount should be accepted -And the form should ask for "Payment information" -And the transaction is deliberately not submitted -When I open the "Withdrawal" form from the dashboard -Then the "Withdrawal" form should be shown -When I enter the withdrawal amount in "1" of "Sheet1" of "Withdraw_TestData.xlsx" -Then the amount should be accepted -And the transaction is deliberately not submitted -When I open the "Convert" form from the dashboard -Then the "Convert" form should be shown -When I enter the conversion amount in "1" of "Sheet1" of "Convert_TestData.xlsx" -Then the amount should be accepted -And the transaction is deliberately not submitted -When I open the transfer hub -Then the transfer hub should offer the route "UMPay to Existing template" -And the transfer hub should offer the route "UMPay to UMPay Wallet" -When I take the "UnionPay China" route -Then the UnionPay transfer form should be shown -When I enter the UnionPay amount in "1" of "Sheet1" of "GlobalTransfer_TestData.xlsx" -Then the transfer should be priced -And the UnionPay transfer should become sendable -And the transfer is deliberately not sent -When I sign out -Then I should be back on the login screen | G9: Convert_TestData.xlsx, Deposit_TestData.xlsx, GlobalTransfer_TestData.xlsx, Login_TestData.xlsx, Withdraw_TestData.xlsx | H9: I should reach the dashboard; the dashboard should offer the money actions; the "Deposit" form should be shown; the "Confirm" action should be disabled; the amount should be accepted; the form should ask for "Payment information"; the transaction is deliberately not submitted; the "Withdrawal" form should be shown | I9: The app is left on the screen the scenario reached | J9: Not run in this pass. The runner holds @register and @e2e back from an unattended run - a registration makes a real account, solves a captcha and reads a code out of a mailbox, and the journey drives every form a second time on the one device this suite has. Launch it on its own with the Run link beside this row | K9: PENDING | L9: HIGH | M9: KIMA | N9: 46274 | O9: Redmi 13C (Android) | P9: UMPay Android app | S9: Run

Sheet Test Result
B2: Login | E2: Register | J2: Result | K2: Test Cases (n) | L2: Test Cases (%)
B3: PASS | C3: =COUNTIF(Login!K:K,"PASS") | E3: PASS | F3: =COUNTIF(Register!K:K,"PASS") | J3: PASS | K3: =SUM(C3,F3,C8,F8,C13,F13,C18,F18,C23) | L3: =IFERROR(K3/$K$6,0)
B4: FAIL | C4: =COUNTIF(Login!K:K,"FAIL") | E4: FAIL | F4: =COUNTIF(Register!K:K,"FAIL") | J4: FAIL | K4: =SUM(C4,F4,C9,F9,C14,F14,C19,F19,C24) | L4: =IFERROR(K4/$K$6,0)
B5: PENDING | C5: =COUNTIF(Login!K:K,"PENDING") | E5: PENDING | F5: =COUNTIF(Register!K:K,"PENDING") | J5: PENDING | K5: =SUM(C5,F5,C10,F10,C15,F15,C20,F20,C25) | L5: =IFERROR(K5/$K$6,0)
J6: TOTAL | K6: =SUM(K3,K4,K5)
B7: Deposit | E7: Withdraw
B8: PASS | C8: =COUNTIF(Deposit!K:K,"PASS") | E8: PASS | F8: =COUNTIF(Withdraw!K:K,"PASS") | J8: Priority | K8: HIGH | L8: MEDIUM | M8: LOW
B9: FAIL | C9: =COUNTIF(Deposit!K:K,"FAIL") | E9: FAIL | F9: =COUNTIF(Withdraw!K:K,"FAIL") | J9: PASS | K9: =SUM(Login!P3,Register!P3,Deposit!P3,Withdraw!P3,Transfer!P3,Convert!P3,Global_Transfer!P3,Profile!P3,End_To_End!P3) | L9: =SUM(Login!Q3,Register!Q3,Deposit!Q3,Withdraw!Q3,Transfer!Q3,Convert!Q3,Global_Transfer!Q3,Profile!Q3,End_To_End!Q3) | M9: =SUM(Login!R3,Register!R3,Deposit!R3,Withdraw!R3,Transfer!R3,Convert!R3,Global_Transfer!R3,Profile!R3,End_To_End!R3)
B10: PENDING | C10: =COUNTIF(Deposit!K:K,"PENDING") | E10: PENDING | F10: =COUNTIF(Withdraw!K:K,"PENDING") | J10: FAIL | K10: =SUM(Login!P4,Register!P4,Deposit!P4,Withdraw!P4,Transfer!P4,Convert!P4,Global_Transfer!P4,Profile!P4,End_To_End!P4) | L10: =SUM(Login!Q4,Register!Q4,Deposit!Q4,Withdraw!Q4,Transfer!Q4,Convert!Q4,Global_Transfer!Q4,Profile!Q4,End_To_End!Q4) | M10: =SUM(Login!R4,Register!R4,Deposit!R4,Withdraw!R4,Transfer!R4,Convert!R4,Global_Transfer!R4,Profile!R4,End_To_End!R4)
J11: PENDING | K11: =SUM(Login!P5,Register!P5,Deposit!P5,Withdraw!P5,Transfer!P5,Convert!P5,Global_Transfer!P5,Profile!P5,End_To_End!P5) | L11: =SUM(Login!Q5,Register!Q5,Deposit!Q5,Withdraw!Q5,Transfer!Q5,Convert!Q5,Global_Transfer!Q5,Profile!Q5,End_To_End!Q5) | M11: =SUM(Login!R5,Register!R5,Deposit!R5,Withdraw!R5,Transfer!R5,Convert!R5,Global_Transfer!R5,Profile!R5,End_To_End!R5)
B12: Transfer | E12: Convert
B13: PASS | C13: =COUNTIF(Transfer!K:K,"PASS") | E13: PASS | F13: =COUNTIF(Convert!K:K,"PASS")
B14: FAIL | C14: =COUNTIF(Transfer!K:K,"FAIL") | E14: FAIL | F14: =COUNTIF(Convert!K:K,"FAIL")
B15: PENDING | C15: =COUNTIF(Transfer!K:K,"PENDING") | E15: PENDING | F15: =COUNTIF(Convert!K:K,"PENDING")
B17: Global_Transfer | E17: Profile
B18: PASS | C18: =COUNTIF(Global_Transfer!K:K,"PASS") | E18: PASS | F18: =COUNTIF(Profile!K:K,"PASS")
B19: FAIL | C19: =COUNTIF(Global_Transfer!K:K,"FAIL") | E19: FAIL | F19: =COUNTIF(Profile!K:K,"FAIL")
B20: PENDING | C20: =COUNTIF(Global_Transfer!K:K,"PENDING") | E20: PENDING | F20: =COUNTIF(Profile!K:K,"PENDING")
B22: End_To_End
B23: PASS | C23: =COUNTIF(End_To_End!K:K,"PASS")
B24: FAIL | C24: =COUNTIF(End_To_End!K:K,"FAIL")
B25: PENDING | C25: =COUNTIF(End_To_End!K:K,"PENDING")

Sheet METADATA
A1: Status | B1: Priority | C1: QA RESOURCES | D1: Platform | E1: Device | F1: Project | G1: Test Category
A2: PASS | B2: LOW | C2: DARA | D2: UMPay Android app | E2: Redmi 13C (Android) | F2: UMPAY | G2: Positive
A3: FAIL | B3: MEDIUM | C3: KIMA | D3: UMPay iOS app | E3: Android Emulator | F3: WPAY | G3: Negative
A4: PENDING | B4: HIGH | C4: VATHANA | E4: iPhone | F4: OFL
F5: UNCS
